flanks/__init__.py
flanks/_version.py
flanks/base.py
flanks/client.py
flanks/connection.py
flanks/exceptions.py
flanks/pagination.py
flanks/py.typed
flanks/aggregation_v1/__init__.py
flanks/aggregation_v1/client.py
flanks/aggregation_v1/models.py
flanks/aggregation_v2/__init__.py
flanks/aggregation_v2/client.py
flanks/aggregation_v2/models.py
flanks/connect/__init__.py
flanks/connect/client.py
flanks/connect/models.py
flanks/credentials/__init__.py
flanks/credentials/client.py
flanks/credentials/models.py
flanks/entities/__init__.py
flanks/entities/client.py
flanks/entities/models.py
flanks/links/__init__.py
flanks/links/client.py
flanks/links/models.py
flanks/report/__init__.py
flanks/report/client.py
flanks/report/models.py
flanks_client-0.1.0.dist-info/METADATA
flanks_client-0.1.0.dist-info/WHEEL
flanks_client-0.1.0.dist-info/licenses/LICENSE
flanks_client-0.1.0.dist-info/RECORD
