Metadata-Version: 2.4
Name: flanks-client
Version: 0.1.0
Summary: Python SDK for Flanks API
Project-URL: Repository, https://github.com/diegok/flanks-python
Author-email: Diego Kuperman <diego.kuperman@flanks.io>
License-Expression: MIT
License-File: LICENSE
Keywords: aggregation,api,banking,flanks,sdk
Classifier: Development Status :: 4 - Beta
Classifier: Intended Audience :: Developers
Classifier: License :: OSI Approved :: MIT License
Classifier: Programming Language :: Python :: 3.10
Classifier: Programming Language :: Python :: 3.11
Classifier: Programming Language :: Python :: 3.12
Classifier: Programming Language :: Python :: 3.13
Classifier: Programming Language :: Python :: 3.14
Classifier: Typing :: Typed
Requires-Python: <4,>=3.10
Requires-Dist: httpx<0.29,>=0.28.1
Requires-Dist: pydantic<3,>=2.10
